.gitignore
.isort.cfg
LICENSE
License.txt
MANIFEST.in
Makefile
README
TODO
Ufit.pyproj
Ufit.sln
covergui.py
pylintrc
requirements-installer.txt
setup.py
ufitgui
docs/Makefile
docs/conf.py
docs/gui.rst
docs/index.rst
docs/intro.rst
docs/models.rst
docs/script.rst
docs/_templates/layout.html
docs/pics/main1.png
installer/ufit-osx.spec
installer/ufit_singlefile.spec
installer/ufit_singlefolder.nsi
installer/ufit_singlefolder.spec
qcoverage/bz.py
qcoverage/hhl-test.py
qcoverage/hk0-and-h0l.py
qcoverage/readme.txt
resource/appicon-16.png
resource/appicon-48.png
resource/appicon.png
resource/arrow-180.png
resource/arrow-circle-double.png
resource/arrow-join.png
resource/arrow-move.png
resource/arrow-switch.png
resource/arrow.png
resource/chart--arrow.png
resource/cross-button.png
resource/cross.png
resource/disk-black.png
resource/disks-black.png
resource/document-export.png
resource/document-pdf.png
resource/document.png
resource/drawer--minus.png
resource/drawer--plus.png
resource/drawer-double-open.png
resource/drawer-open.png
resource/drawer.png
resource/folder-open.png
resource/gear.png
resource/gui.qrc
resource/home.png
resource/image-sunset.png
resource/log-x.png
resource/log-y.png
resource/log-z.png
resource/magnifier-zoom-fit.png
resource/map.png
resource/notebook--plus.png
resource/notebook.png
resource/printer.png
resource/question-white.png
resource/script-php.png
resource/selection-resize.png
resource/splash.png
resource/splash.xcf
resource/table-select-row.png
resource/terminal--arrow.png
resource/ufit.desktop
resource/ufit.icns
resource/ufit.png
ufit/RELEASE-VERSION
ufit/__init__.py
ufit/bzplot.py
ufit/cluster.py
ufit/guires_qt5.py
ufit/guires_qt6.py
ufit/lab.py
ufit/param.py
ufit/plotting.py
ufit/qreader.py
ufit/qt.py
ufit/rescalc.py
ufit/result.py
ufit/utils.py
ufit/version.py
ufit.egg-info/PKG-INFO
ufit.egg-info/SOURCES.txt
ufit.egg-info/dependency_links.txt
ufit.egg-info/entry_points.txt
ufit.egg-info/requires.txt
ufit.egg-info/top_level.txt
ufit/backends/__init__.py
ufit/backends/lmfit.py
ufit/backends/minuit.py
ufit/backends/scipy.py
ufit/backends/unifit.py
ufit/data/__init__.py
ufit/data/cascade.py
